devkit/__init__.py
devkit/hostconfig.py
devkit/cli/__init__.py
devkit/cli/parse.py
devkit/core/__init__.py
devkit/core/module.py
devkit/core/softwares/__init__.py
devkit/core/softwares/docker.py
devkit/core/softwares/insomnia.py
devkit/core/softwares/software.py
devkit/web/__init__.py
devkit/web/create_app.py
devkit/webui/__init__.py
devkit/webui/favicon.ico
devkit/webui/index.html
devkit/webui/css/__init__.py
devkit/webui/css/app.b229284b.css
devkit/webui/css/chunk-vendors.5699e6ca.css
devkit/webui/img/__init__.py
devkit/webui/img/logo.82b9c7a5.png
devkit/webui/js/__init__.py
devkit/webui/js/about.25f0b57a.js
devkit/webui/js/about.25f0b57a.js.map
devkit/webui/js/app.b2076797.js
devkit/webui/js/app.b2076797.js.map
devkit/webui/js/chunk-vendors.c7843970.js
devkit/webui/js/chunk-vendors.c7843970.js.map
devkit-0.0.12.dist-info/LICENSE
devkit-0.0.12.dist-info/METADATA
devkit-0.0.12.dist-info/WHEEL
devkit-0.0.12.dist-info/entry_points.txt
devkit-0.0.12.dist-info/top_level.txt
devkit-0.0.12.dist-info/RECORD
