Metadata-Version: 2.1
Name: devkit
Version: 0.0.12
Summary: A tool to efficiently manage development environment
Home-page: https://gitlab.com/hoshiyosan/devtools/devkit/devkit-python
Author: Sylvan LE DEUNFF
Author-email: sledeunf@gmail.com
License: UNKNOWN
Project-URL: Documentation, https://hoshiyosan.gitlab.io/devtools/devkit/devkit-python
Project-URL: Source, https://gitlab.com/hoshiyosan/devtools/devkit/devkit-python
Platform: UNKNOWN
Classifier: Programming Language :: Python :: 3
Classifier: License :: OSI Approved :: MIT License
Classifier: Operating System :: OS Independent
Requires-Python: >=3.6
Requires-Dist: flask (==1.1.2)
